nebula_realtime_autopilot/__init__.py
nebula_realtime_autopilot/hello.py
nebula_realtime_autopilot-0.0.1b0.dist-info/METADATA
nebula_realtime_autopilot-0.0.1b0.dist-info/WHEEL
nebula_realtime_autopilot-0.0.1b0.dist-info/top_level.txt
nebula_realtime_autopilot-0.0.1b0.dist-info/RECORD
