Metadata-Version: 2.1
Name: nebula_realtime_autopilot
Version: 0.0.1b0
Summary: Symbl.ai Realtime Autopilot for Nebula
Home-page: https://github.com/subodhjena/nebula_realtime_autopilot
Author: Subodh Jena
Author-email: jenasubodh@gmail.com
Project-URL: Bug Tracker, https://github.com/subodhjena/nebula_realtime_autopilot/issues
Classifier: Programming Language :: Python :: 3
Classifier: License :: OSI Approved :: MIT License
Classifier: Operating System :: OS Independent
Classifier: Development Status :: 3 - Alpha
Requires-Python: >=3.8
